pyglossary/__init__.py
pyglossary/apple_utils.py
pyglossary/arabic_utils.py
pyglossary/compression.py
pyglossary/config_type.py
pyglossary/core.py
pyglossary/core_test.py
pyglossary/ebook_base.py
pyglossary/entry.py
pyglossary/entry_base.py
pyglossary/entry_filters.py
pyglossary/entry_list.py
pyglossary/entry_merge.py
pyglossary/file_utils.py
pyglossary/flags.py
pyglossary/glossary.py
pyglossary/glossary_info.py
pyglossary/glossary_progress.py
pyglossary/glossary_types.py
pyglossary/glossary_utils.py
pyglossary/glossary_v2.py
pyglossary/gregorian.py
pyglossary/html_utils.py
pyglossary/icu_types.py
pyglossary/image_utils.py
pyglossary/info.py
pyglossary/info_writer.py
pyglossary/io_utils.py
pyglossary/iter_utils.py
pyglossary/json_utils.py
pyglossary/logger.py
pyglossary/lxml_types.py
pyglossary/option.py
pyglossary/os_utils.py
pyglossary/persian_utils.py
pyglossary/plugin_handler.py
pyglossary/plugin_prop.py
pyglossary/queued_iter.py
pyglossary/reverse.py
pyglossary/sdsqlite.py
pyglossary/slob.py
pyglossary/sort_keys.py
pyglossary/sort_keys_types.py
pyglossary/sq_entry_list.py
pyglossary/text_reader.py
pyglossary/text_utils.py
pyglossary/text_writer.py
pyglossary/ui_type.py
pyglossary/xml_utils.py
pyglossary/langs/__init__.py
pyglossary/langs/langs.json
pyglossary/langs/writing_system.py
pyglossary/plugin_lib/__init__.py
pyglossary/plugin_lib/dictdlib.py
pyglossary/plugin_lib/mutf8.py
pyglossary/plugin_lib/pureSalsa20.py
pyglossary/plugin_lib/readmdict.py
pyglossary/plugin_lib/ripemd128.py
pyglossary/plugins/__init__.py
pyglossary/plugins/aard2_slob/__init__.py
pyglossary/plugins/aard2_slob/reader.py
pyglossary/plugins/aard2_slob/tags.py
pyglossary/plugins/aard2_slob/tools.toml
pyglossary/plugins/aard2_slob/writer.py
pyglossary/plugins/almaany/__init__.py
pyglossary/plugins/almaany/reader.py
pyglossary/plugins/almaany/tools.toml
pyglossary/plugins/appledict/__init__.py
pyglossary/plugins/appledict/_content.py
pyglossary/plugins/appledict/_dict.py
pyglossary-5.2.1.dist-info/licenses/AUTHORS
pyglossary-5.2.1.dist-info/licenses/LICENSE
pyglossary-5.2.1.dist-info/METADATA
pyglossary-5.2.1.dist-info/WHEEL
pyglossary-5.2.1.dist-info/entry_points.txt
pyglossary-5.2.1.dist-info/top_level.txt
pyglossary-5.2.1.dist-info/RECORD
