Metadata-Version: 2.4
Name: pyglossary
Version: 5.2.1
Summary: A tool for converting dictionary files aka glossaries.
Home-page: https://github.com/ilius/pyglossary
Author: Saeed Rasooli
Author-email: Saeed Rasooli <saeed.gnu@gmail.com>
License-Expression: GPL-3.0-or-later
Project-URL: Homepage, https://github.com/ilius/pyglossary
Project-URL: Issues, https://github.com/ilius/pyglossary/issues
Project-URL: Changelog, https://github.com/ilius/pyglossary/tree/master/doc/releases
Keywords: dictionary,glossary
Classifier: Development Status :: 5 - Production/Stable
Classifier: Operating System :: OS Independent
Classifier: Typing :: Typed
Classifier: Programming Language :: Python :: 3.11
Classifier: Programming Language :: Python :: 3.12
Classifier: Programming Language :: Python :: 3.13
Requires-Python: >=3.10.0
License-File: LICENSE
License-File: AUTHORS
Provides-Extra: all
Requires-Dist: PyICU; extra == "all"
Requires-Dist: lxml; extra == "all"
Requires-Dist: beautifulsoup4; extra == "all"
Dynamic: author
Dynamic: home-page
Dynamic: license-file
Dynamic: requires-python
